ddresolve.py
ddresolve-0.1.20251116.dist-info/METADATA
ddresolve-0.1.20251116.dist-info/WHEEL
ddresolve-0.1.20251116.dist-info/licenses/COPYING
ddresolve-0.1.20251116.dist-info/licenses/LICENCE
ddresolve-0.1.20251116.dist-info/RECORD
