Metadata-Version: 2.4
Name: ddresolve
Version: 0.1.20251116
Summary: Distributed Directory name resolver
Project-URL: source, https://codeberg.org/skyguy/ddresolve
Author-email: Kevin Steen <code@kevinsteen.net>
License-Expression: AGPL-3.0-or-later
License-File: COPYING
License-File: LICENCE
Keywords: ddig,dig,dns,petnames
Classifier: Development Status :: 3 - Alpha
Classifier: Intended Audience :: Developers
Classifier: License :: OSI Approved :: GNU Affero General Public License v3 or later (AGPLv3+)
Classifier: Operating System :: OS Independent
Classifier: Programming Language :: Python :: 3 :: Only
Classifier: Topic :: Communications
Requires-Python: >=3.12
Provides-Extra: dev
Requires-Dist: pytest; extra == 'dev'
